lint_it/__init__.py
lint_it/linter.py
lintit-0.0.35.dist-info/LICENSE
lintit-0.0.35.dist-info/METADATA
lintit-0.0.35.dist-info/WHEEL
lintit-0.0.35.dist-info/entry_points.txt
lintit-0.0.35.dist-info/top_level.txt
lintit-0.0.35.dist-info/RECORD
