Metadata-Version: 2.1
Name: lintit
Version: 0.0.35
Summary: A cli linter
Home-page: https://github.com/EvertonTomalok/lint-it
Author: Everton Tomalok
Author-email: evertontomalok123@gmail.com
License: UNKNOWN
Platform: UNKNOWN
Classifier: Programming Language :: Python :: 3
Classifier: License :: OSI Approved :: MIT License
Classifier: Operating System :: OS Independent
Requires-Python: >=3.6
